Workbook

Sheet Raw_Data
A1: 📊 FINANCIAL MODEL | Raw Transaction Data
A2: 🔵 Blue = Input | C2: ⚫ Black = Formula | E2: 🟢 Green = X-Sheet Link
A3: Date | B3: Product_Category | C3: Product | D3: Region | E3: Units_Sold | F3: Price ($) | G3: Variable_Cost ($) | H3: Fixed_Cost ($) | I3: Revenue ($) | J3: Total_Cost ($) | K3: Profit ($) | L3: Margin (%)
A4: 45619 | B4: Electronics | C4: Laptop | D4: Sylhet | E4: 135 | F4: 194.1 | G4: 110.82 | H4: 1418.06 | I4: =E4*F4 -> 26203.5 | J4: =(E4*G4)+H4 -> 16378.76 | K4: =I4-J4 -> 9824.74 | L4: =IF(I4<>0,K4/I4,0) -> 0.37493999
A5: 45571 | B5: Electronics | C5: Headphones | D5: Dhaka | E5: 25 | F5: 93.08 | G5: 39.07 | H5: 1283.63 | I5: =E5*F5 -> 2327 | J5: =(E5*G5)+H5 -> 2260.38 | K5: =I5-J5 -> 66.62 | L5: =IF(I5<>0,K5/I5,0) -> 0.028629136
A6: 45579 | B6: Electronics | C6: Headphones | D6: Chittagong | E6: 239 | F6: 479.63 | G6: 284.34 | H6: 211.7 | I6: =E6*F6 -> 114631.57 | J6: =(E6*G6)+H6 -> 68168.96 | K6: =I6-J6 -> 46462.61 | L6: =IF(I6<>0,K6/I6,0) -> 0.40532124
A7: 45373 | B7: FMCG | C7: Oil | D7: Sylhet | E7: 152 | F7: 141.27 | G7: 90.01 | H7: 805.87 | I7: =E7*F7 -> 21473.04 | J7: =(E7*G7)+H7 -> 14487.39 | K7: =I7-J7 -> 6985.65 | L7: =IF(I7<>0,K7/I7,0) -> 0.32532189
A8: 45339 | B8: Apparel | C8: T-Shirt | D8: Sylhet | E8: 443 | F8: 288.29 | G8: 123.78 | H8: 278.21 | I8: =E8*F8 -> 127712.47 | J8: =(E8*G8)+H8 -> 55112.75 | K8: =I8-J8 -> 72599.72 | L8: =IF(I8<>0,K8/I8,0) -> 0.56846227
A9: 45527 | B9: FMCG | C9: Soap | D9: Khulna | E9: 50 | F9: 450.59 | G9: 269.82 | H9: 1313.34 | I9: =E9*F9 -> 22529.5 | J9: =(E9*G9)+H9 -> 14804.34 | K9: =I9-J9 -> 7725.16 | L9: =IF(I9<>0,K9/I9,0) -> 0.34289088
A10: 45477 | B10: FMCG | C10: Shampoo | D10: Dhaka | E10: 33 | F10: 535.79 | G10: 311.79 | H10: 1973.4 | I10: =E10*F10 -> 17681.07 | J10: =(E10*G10)+H10 -> 12262.47 | K10: =I10-J10 -> 5418.6 | L10: =IF(I10<>0,K10/I10,0) -> 0.30646335
A11: 45411 | B11: Electronics | C11: Headphones | D11: Sylhet | E11: 242 | F11: 515.83 | G11: 237 | H11: 866.33 | I11: =E11*F11 -> 124830.86 | J11: =(E11*G11)+H11 -> 58220.33 | K11: =I11-J11 -> 66610.53 | L11: =IF(I11<>0,K11/I11,0) -> 0.53360627
A12: 45399 | B12: FMCG | C12: Rice | D12: Dhaka | E12: 321 | F12: 515.28 | G12: 262.92 | H12: 640.66 | I12: =E12*F12 -> 165404.88 | J12: =(E12*G12)+H12 -> 85037.98 | K12: =I12-J12 -> 80366.9 | L12: =IF(I12<>0,K12/I12,0) -> 0.48587986
A13: 45528 | B13: Apparel | C13: Shoes | D13: Rajshahi | E13: 122 | F13: 554 | G13: 333.98 | H13: 1596.8 | I13: =E13*F13 -> 67588 | J13: =(E13*G13)+H13 -> 42342.36 | K13: =I13-J13 -> 25245.64 | L13: =IF(I13<>0,K13/I13,0) -> 0.37352252
A14: 45409 | B14: Electronics | C14: Tablet | D14: Khulna | E14: 147 | F14: 71.63 | G14: 44.69 | H14: 1220.92 | I14: =E14*F14 -> 10529.61 | J14: =(E14*G14)+H14 -> 7790.35 | K14: =I14-J14 -> 2739.26 | L14: =IF(I14<>0,K14/I14,0) -> 0.26014829
A15: 45453 | B15: Electronics | C15: Headphones | D15: Khulna | E15: 462 | F15: 733.35 | G15: 357.62 | H15: 676.78 | I15: =E15*F15 -> 338807.7 | J15: =(E15*G15)+H15 -> 165897.22 | K15: =I15-J15 -> 172910.48 | L15: =IF(I15<>0,K15/I15,0) -> 0.51034991
... A103: 45522 | B103: Apparel | C103: Shoes | D103: Rajshahi | E103: 229 | F103: 258.2 | G103: 138.47 | H103: 1297.34 | I103: =E103*F103 -> 59127.8 | J103: =(E103*G103)+H103 -> 33006.97 | K103: =I103-J103 -> 26120.83 | L103: =IF(I103<>0,K103/I103,0) -> 0.44176902
A104: TOTALS | E104: =SUM(E4:E103) -> 25923 | F104: =SUM(F4:F103) -> 43863.67 | G104: =SUM(G4:G103) -> 21946.09 | H104: =SUM(H4:H103) -> 97897.18 | I104: =SUM(I4:I103) -> 11247324 | J104: =SUM(J4:J103) -> 5657718.6 | K104: =SUM(K4:K103) -> 5589605.3 | L104: =SUM(L4:L103) -> 46.284394

Sheet Calculations
A1: 📐 Calculations | Summary & Regional Breakdown
A2: SUMMARY METRICS
A3: Total Revenue | B3: =SUM(Raw_Data!I4:I103) -> 11247324
A4: Total Cost | B4: =SUM(Raw_Data!J4:J103) -> 5657718.6
A5: Total Profit | B5: =SUM(Raw_Data!K4:K103) -> 5589605.3
A6: Avg Margin | B6: =AVERAGE(Raw_Data!L4:L103) -> 0.46284394
A7: Total Units | B7: =SUM(Raw_Data!E4:E103) -> 25923
A8: Avg Revenue/Unit | B8: =B3/B7 -> 433.87432
A9: Gross Profit % | B9: =B5/B3 -> 0.49697202
A11: REGIONAL BREAKDOWN
A12: Region | B12: Revenue ($) | C12: Cost ($) | D12: Profit ($) | E12: Margin (%) | F12: Units Sold
A13: Dhaka | B13: =SUMIFS(Raw_Data!I:I,Raw_Data!D:D,A13) -> 1744945.5 | C13: =SUMIFS(Raw_Data!J:J,Raw_Data!D:D,A13) -> 978752.51 | D13: =SUMIFS(Raw_Data!K:K,Raw_Data!D:D,A13) -> 766192.98 | E13: =D13/B13 -> 0.43909279 | F13: =SUMIFS(Raw_Data!E:E,Raw_Data!D:D,A13) -> 5301
A14: Chittagong | B14: =SUMIFS(Raw_Data!I:I,Raw_Data!D:D,A14) -> 2422198.9 | C14: =SUMIFS(Raw_Data!J:J,Raw_Data!D:D,A14) -> 1187496.1 | D14: =SUMIFS(Raw_Data!K:K,Raw_Data!D:D,A14) -> 1234702.8 | E14: =D14/B14 -> 0.5097446 | F14: =SUMIFS(Raw_Data!E:E,Raw_Data!D:D,A14) -> 6204
A15: Sylhet | B15: =SUMIFS(Raw_Data!I:I,Raw_Data!D:D,A15) -> 2188732.1 | C15: =SUMIFS(Raw_Data!J:J,Raw_Data!D:D,A15) -> 1063280.2 | D15: =SUMIFS(Raw_Data!K:K,Raw_Data!D:D,A15) -> 1125451.9 | E15: =D15/B15 -> 0.51420267 | F15: =SUMIFS(Raw_Data!E:E,Raw_Data!D:D,A15) -> 4260
A16: Khulna | B16: =SUMIFS(Raw_Data!I:I,Raw_Data!D:D,A16) -> 2796225.5 | C16: =SUMIFS(Raw_Data!J:J,Raw_Data!D:D,A16) -> 1443724.2 | D16: =SUMIFS(Raw_Data!K:K,Raw_Data!D:D,A16) -> 1352501.4 | E16: =D16/B16 -> 0.48368822 | F16: =SUMIFS(Raw_Data!E:E,Raw_Data!D:D,A16) -> 5157
A17: Rajshahi | B17: =SUMIFS(Raw_Data!I:I,Raw_Data!D:D,A17) -> 2095221.9 | C17: =SUMIFS(Raw_Data!J:J,Raw_Data!D:D,A17) -> 984465.64 | D17: =SUMIFS(Raw_Data!K:K,Raw_Data!D:D,A17) -> 1110756.2 | E17: =D17/B17 -> 0.53013777 | F17: =SUMIFS(Raw_Data!E:E,Raw_Data!D:D,A17) -> 5001
A18: TOTAL | B18: =SUM(B13:B17) -> 11247324 | C18: =SUM(C13:C17) -> 5657718.6 | D18: =SUM(D13:D17) -> 5589605.3 | E18: =SUM(E13:E17) -> 2.476866 | F18: =SUM(F13:F17) -> 25923
A21: CATEGORY BREAKDOWN
A22: Category | B22: Revenue ($) | C22: Profit ($) | D22: Margin (%) | E22: % of Total Rev | F22: Units Sold
A23: Electronics | B23: =SUMIFS(Raw_Data!I:I,Raw_Data!B:B,A23) -> 4624425.7 | C23: =SUMIFS(Raw_Data!K:K,Raw_Data!B:B,A23) -> 2287080.8 | D23: =C23/B23 -> 0.49456536 | E23: =B23/B$3 -> 0.41115786 | F23: =SUMIFS(Raw_Data!E:E,Raw_Data!B:B,A23) -> 9195
A24: Apparel | B24: =SUMIFS(Raw_Data!I:I,Raw_Data!B:B,A24) -> 3416895.4 | C24: =SUMIFS(Raw_Data!K:K,Raw_Data!B:B,A24) -> 1662448.6 | D24: =C24/B24 -> 0.48653775 | E24: =B24/B$3 -> 0.3037963 | F24: =SUMIFS(Raw_Data!E:E,Raw_Data!B:B,A24) -> 6975
A25: FMCG | B25: =SUMIFS(Raw_Data!I:I,Raw_Data!B:B,A25) -> 3206002.9 | C25: =SUMIFS(Raw_Data!K:K,Raw_Data!B:B,A25) -> 1640075.9 | D25: =C25/B25 -> 0.51156409 | E25: =B25/B$3 -> 0.28504584 | F25: =SUMIFS(Raw_Data!E:E,Raw_Data!B:B,A25) -> 9753

Sheet Assumptions
A1: ⚙️ Assumptions | All Model Drivers
A2: Assumption | B2: Value | C2: Sensitivity Range | D2: Notes
A3: ── GROWTH ──
A4: Revenue Growth Rate | B4: 0.08 | C4: 4%–15% | D4: Base case; adj. for macro
A5: Price Growth Rate | B5: 0.05 | C5: 2%–10% | D5: CPI-linked pricing
A6: ── COST ──
A7: Cost Inflation Rate | B7: 0.06 | C7: 3%–10% | D7: Supply-chain assumption
A8: Capex (BDT) | B8: 500000 | C8: 300k–800k | D8: Annual maintenance capex
A9: Depreciation (BDT) | B9: 200000 | C9: 150k–300k | D9: Straight-line 5 yrs
A10: Working Capital % | B10: 0.12 | C10: 8%–18% | D10: % of Revenue
A11: ── TAX ──
A12: Tax Rate | B12: 0.2 | C12: 15%–25% | D12: Effective corporate rate
A13: ── WACC ──
A14: WACC | B14: 0.12 | C14: 9%–15% | D14: Weighted avg cost of capital
A15: Terminal Growth Rate | B15: 0.04 | C15: 2%–6% | D15: Long-run GDP-linked growth
A16: Risk-Free Rate | B16: 0.065 | C16: 5%–8% | D16: Bangladesh T-bill proxy
A17: Equity Risk Premium | B17: 0.055 | C17: 4%–7% | D17: EM market premium
A18: Beta | B18: 1.15 | C18: 0.8–1.5 | D18: Industry beta estimate

Sheet Financial_Model
A1: 📈 5-Year Financial Forecast Model
A2: ── INCOME STATEMENT ── | B2: Base (Yr 0) | C2: Year 1 | D2: Year 2 | E2: Year 3 | F2: Year 4 | G2: Year 5 | H2: CAGR | I2: Notes
A3: Revenue ($) | B3: =Calculations!B3 -> 11247324 | C3: =B3*(1+Assumptions!$B$4) -> 12147110 | D3: =C3*(1+Assumptions!$B$4) -> 13118879 | E3: =D3*(1+Assumptions!$B$4) -> 14168389 | F3: =E3*(1+Assumptions!$B$4) -> 15301860 | G3: =F3*(1+Assumptions!$B$4) -> 16526009 | H3: =IFERROR((G3/B3)^(1/5)-1,0) -> 0.08 | I3: Top-line growth driver
A4: COGS ($) | B4: =Calculations!B4 -> 5657718.6 | C4: =B4*(1+Assumptions!$B$7) -> 5997181.8 | D4: =C4*(1+Assumptions!$B$7) -> 6357012.7 | E4: =D4*(1+Assumptions!$B$7) -> 6738433.4 | F4: =E4*(1+Assumptions!$B$7) -> 7142739.4 | G4: =F4*(1+Assumptions!$B$7) -> 7571303.8 | H4: =IFERROR((G4/B4)^(1/5)-1,0) -> 0.06 | I4: Variable + fixed costs
A5: Gross Profit ($) | B5: =B3-B4 -> 5589605.3 | C5: =C3-C4 -> 6149928.1 | D5: =D3-D4 -> 6761866 | E5: =E3-E4 -> 7429955.5 | F5: =F3-F4 -> 8159120.6 | G5: =G3-G4 -> 8954705 | H5: =IFERROR((G5/B5)^(1/5)-1,0) -> 0.098838908 | I5: Revenue minus COGS
A6: Gross Margin (%) | B6: =B5/B3 -> 0.49697202 | C6: =C5/C3 -> 0.50628735 | D6: =D5/D3 -> 0.51543018 | E6: =E5/E3 -> 0.52440369 | F6: =F5/F3 -> 0.53321103 | G6: =G5/G3 -> 0.54185527 | I6: Gross Profit / Revenue
A7: EBITDA ($) | B7: =B5 -> 5589605.3 | C7: =C5 -> 6149928.1 | D7: =D5 -> 6761866 | E7: =E5 -> 7429955.5 | F7: =F5 -> 8159120.6 | G7: =G5 -> 8954705 | H7: =IFERROR((G7/B7)^(1/5)-1,0) -> 0.098838908 | I7: Proxy: Gross Profit
A8: EBITDA Margin (%) | B8: =B7/B3 -> 0.49697202 | C8: =C7/C3 -> 0.50628735 | D8: =D7/D3 -> 0.51543018 | E8: =E7/E3 -> 0.52440369 | F8: =F7/F3 -> 0.53321103 | G8: =G7/G3 -> 0.54185527 | I8: EBITDA / Revenue
A9: Tax ($) | B9: =B7*Assumptions!$B$12 -> 1117921.1 | C9: =C7*Assumptions!$B$12 -> 1229985.6 | D9: =D7*Assumptions!$B$12 -> 1352373.2 | E9: =E7*Assumptions!$B$12 -> 1485991.1 | F9: =F7*Assumptions!$B$12 -> 1631824.1 | G9: =G7*Assumptions!$B$12 -> 1790941 | H9: =IFERROR((G9/B9)^(1/5)-1,0) -> 0.098838908 | I9: Applied to EBITDA
A10: Net Income ($) | B10: =B7-B9 -> 4471684.2 | C10: =C7-C9 -> 4919942.5 | D10: =D7-D9 -> 5409492.8 | E10: =E7-E9 -> 5943964.4 | F10: =F7-F9 -> 6527296.5 | G10: =G7-G9 -> 7163764 | H10: =IFERROR((G10/B10)^(1/5)-1,0) -> 0.098838908 | I10: Post-tax profit
A11: ── CASH FLOW ──
A12: Depreciation ($) | B12: =Assumptions!$B$9 -> 200000 | C12: =Assumptions!$B$9 -> 200000 | D12: =Assumptions!$B$9 -> 200000 | E12: =Assumptions!$B$9 -> 200000 | F12: =Assumptions!$B$9 -> 200000 | G12: =Assumptions!$B$9 -> 200000 | H12: =IFERROR((G12/B12)^(1/5)-1,0) -> 0 | I12: Non-cash add-back
A13: Working Capital ($) | B13: =B3*Assumptions!$B$10 -> 1349678.9 | C13: =C3*Assumptions!$B$10 -> 1457653.2 | D13: =D3*Assumptions!$B$10 -> 1574265.4 | E13: =E3*Assumptions!$B$10 -> 1700206.7 | F13: =F3*Assumptions!$B$10 -> 1836223.2 | G13: =G3*Assumptions!$B$10 -> 1983121.1 | H13: =IFERROR((G13/B13)^(1/5)-1,0) -> 0.08 | I13: % of Revenue
A14: ΔWorking Capital ($) | B14: 0 | C14: =C13-B13 -> 107974.31 | D14: =D13-C13 -> 116612.25 | E14: =E13-D13 -> 125941.23 | F14: =F13-E13 -> 136016.53 | G14: =G13-F13 -> 146897.86 | H14: =IFERROR((G14/B14)^(1/5)-1,0) -> 0 | I14: Change in WC
A15: Capex ($) | B15: =Assumptions!$B$8 -> 500000 | C15: =Assumptions!$B$8 -> 500000 | D15: =Assumptions!$B$8 -> 500000 | E15: =Assumptions!$B$8 -> 500000 | F15: =Assumptions!$B$8 -> 500000 | G15: =Assumptions!$B$8 -> 500000 | H15: =IFERROR((G15/B15)^(1/5)-1,0) -> 0 | I15: Annual investment
A16: Free Cash Flow ($) | B16: =B10+B12-B14-B15 -> 4171684.2 | C16: =C10+C12-C14-C15 -> 4511968.2 | D16: =D10+D12-D14-D15 -> 4992880.5 | E16: =E10+E12-E14-E15 -> 5518023.2 | F16: =F10+F12-F14-F15 -> 6091279.9 | G16: =G10+G12-G14-G15 -> 6716866.2 | H16: =IFERROR((G16/B16)^(1/5)-1,0) -> 0.099945212 | I16: NI+Depr−ΔWC−Capex

Sheet Valuation_DCF
A1: 💰 Discounted Cash Flow Valuation
A2: Period | B2: Free Cash Flow ($) | C2: Discount Factor | D2: PV of FCF ($) | E2: Cumulative PV ($) | F2: Notes
A3: Year 1 | B3: =Financial_Model!C16 -> 4511968.2 | C3: =1/(1+Assumptions!$B$14)^1 -> 0.89285714 | D3: =B3*C3 -> 4028543 | E3: =SUM(D3:D3) -> 4028543 | F3: Year 1 discounted @ WACC
A4: Year 2 | B4: =Financial_Model!D16 -> 4992880.5 | C4: =1/(1+Assumptions!$B$14)^2 -> 0.79719388 | D4: =B4*C4 -> 3980293.8 | E4: =SUM(D3:D4) -> 8008836.8 | F4: Year 2 discounted @ WACC
A5: Year 3 | B5: =Financial_Model!E16 -> 5518023.2 | C5: =1/(1+Assumptions!$B$14)^3 -> 0.71178025 | D5: =B5*C5 -> 3927619.9 | E5: =SUM(D3:D5) -> 11936457 | F5: Year 3 discounted @ WACC
A6: Year 4 | B6: =Financial_Model!F16 -> 6091279.9 | C6: =1/(1+Assumptions!$B$14)^4 -> 0.63551808 | D6: =B6*C6 -> 3871118.5 | E6: =SUM(D3:D6) -> 15807575 | F6: Year 4 discounted @ WACC
A7: Year 5 | B7: =Financial_Model!G16 -> 6716866.2 | C7: =1/(1+Assumptions!$B$14)^5 -> 0.56742686 | D7: =B7*C7 -> 3811330.2 | E7: =SUM(D3:D7) -> 19618905 | F7: Final projection year
A8: TERMINAL VALUE
A9: Terminal FCF ($) | B9: =Financial_Model!G16 -> 6716866.2
A10: Terminal Value ($) | B10: =B9*(1+Assumptions!$B$15)/(Assumptions!$B$14-Assumptions!$B$15) -> 87319260
A11: PV of TV ($) | B11: =B10/(1+Assumptions!$B$14)^5 -> 49547293
A13: ENTERPRISE VALUE SUMMARY
A14: PV of FCFs ($) | B14: =SUM(D3:D7) -> 19618905
A15: PV of Terminal Value ($) | B15: =B11 -> 49547293
A16: Enterprise Value ($) | B16: =B14+B15 -> 69166199
A17: EV / EBITDA (x) | B17: =B16/Financial_Model!B7 -> 12.374076
A18: EV / Revenue (x) | B18: =B16/Financial_Model!B3 -> 6.1495694
A19: TV as % of EV | B19: =B15/B16 -> 0.71635126
B22: =B11 -> 49547293

Sheet Comps
A1: 📊 Comparable Company Analysis (Trading Comps)
A2: Company | B2: Revenue ($) | C2: EBITDA ($) | D2: EBITDA Margin (%) | E2: EV/EBITDA (x) | F2: EV/Revenue (x) | G2: Implied EV ($)
A3: Grameenphone | B3: 45000000 | C3: 18000000 | D3: =IFERROR(C3/B3,0) -> 0.4 | E3: 15 | F3: 14.5 | G3: =C3*E3 -> 270000000
A4: Robi Axiata | B4: 32000000 | C4: 11200000 | D4: =IFERROR(C4/B4,0) -> 0.35 | E4: 16 | F4: 12.8 | G4: =C4*E4 -> 179200000
A5: Banglalink | B5: 28000000 | C5: 8960000 | D5: =IFERROR(C5/B5,0) -> 0.32 | E5: 13.5 | F5: 11.2 | G5: =C5*E5 -> 120960000
A6: BRAC Bank | B6: 38000000 | C6: 13300000 | D6: =IFERROR(C6/B6,0) -> 0.35 | E6: 12 | F6: 9.5 | G6: =C6*E6 -> 159600000
A7: Dutch-Bangla | B7: 22000000 | C7: 7040000 | D7: =IFERROR(C7/B7,0) -> 0.32 | E7: 11 | F7: 8.8 | G7: =C7*E7 -> 77440000
A8: Mean | B8: =AVERAGE(B3:B7) -> 33000000 | C8: =AVERAGE(C3:C7) -> 11700000 | D8: =AVERAGE(D3:D7) -> 0.348 | E8: =AVERAGE(E3:E7) -> 13.5 | F8: =AVERAGE(F3:F7) -> 11.36 | G8: =AVERAGE(G3:G7) -> 161440000
A9: Median | B9: =MEDIAN(B3:B8) -> 32500000 | C9: =MEDIAN(C3:C8) -> 11450000 | D9: =MEDIAN(D3:D8) -> 0.349 | E9: =MEDIAN(E3:E8) -> 13.5 | F9: =MEDIAN(F3:F8) -> 11.28 | G9: =MEDIAN(G3:G8) -> 160520000
A10: Min | B10: =MIN(B3:B9) -> 22000000 | C10: =MIN(C3:C9) -> 7040000 | D10: =MIN(D3:D9) -> 0.32 | E10: =MIN(E3:E9) -> 11 | F10: =MIN(F3:F9) -> 8.8 | G10: =MIN(G3:G9) -> 77440000
A11: Max | B11: =MAX(B3:B10) -> 45000000 | C11: =MAX(C3:C10) -> 18000000 | D11: =MAX(D3:D10) -> 0.4 | E11: =MAX(E3:E10) -> 16 | F11: =MAX(F3:F10) -> 14.5 | G11: =MAX(G3:G10) -> 270000000
A13: TARGET COMPANY VALUATION
A14: Our EBITDA ($) | B14: =Financial_Model!B7 -> 5589605.3
A15: Implied EV — EBITDA Multiple ($) | B15: =B14*MEDIAN(E3:E8) -> 75459671
A16: Implied EV — Revenue Multiple ($) | B16: =Financial_Model!B3*MEDIAN(F3:F8) -> 1.2686981e+08

Sheet Analysis
A1: 📉 Sensitivity Analysis & Scenario Planning
A2: SENSITIVITY: Revenue to Growth Rate (Year 5)
A3: Growth Rate → | B3: 0.04 | C3: 0.06 | D3: 0.08 | E3: 0.1 | F3: 0.12 | G3: 0.15 | H3: 0.2
A4: Year 1 | B4: =Financial_Model!$B$3*(1+0.04)^1 -> 11697217 | C4: =Financial_Model!$B$3*(1+0.06)^1 -> 11922163 | D4: =Financial_Model!$B$3*(1+0.08)^1 -> 12147110 | E4: =Financial_Model!$B$3*(1+0.1)^1 -> 12372056 | F4: =Financial_Model!$B$3*(1+0.12)^1 -> 12597003 | G4: =Financial_Model!$B$3*(1+0.15)^1 -> 12934423 | H4: =Financial_Model!$B$3*(1+0.2)^1 -> 13496789
A5: Year 2 | B5: =Financial_Model!$B$3*(1+0.04)^2 -> 12165106 | C5: =Financial_Model!$B$3*(1+0.06)^2 -> 12637493 | D5: =Financial_Model!$B$3*(1+0.08)^2 -> 13118879 | E5: =Financial_Model!$B$3*(1+0.1)^2 -> 13609262 | F5: =Financial_Model!$B$3*(1+0.12)^2 -> 14108643 | G5: =Financial_Model!$B$3*(1+0.15)^2 -> 14874586 | H5: =Financial_Model!$B$3*(1+0.2)^2 -> 16196146
A6: Year 3 | B6: =Financial_Model!$B$3*(1+0.04)^3 -> 12651710 | C6: =Financial_Model!$B$3*(1+0.06)^3 -> 13395743 | D6: =Financial_Model!$B$3*(1+0.08)^3 -> 14168389 | E6: =Financial_Model!$B$3*(1+0.1)^3 -> 14970188 | F6: =Financial_Model!$B$3*(1+0.12)^3 -> 15801680 | G6: =Financial_Model!$B$3*(1+0.15)^3 -> 17105774 | H6: =Financial_Model!$B$3*(1+0.2)^3 -> 19435376
A7: Year 4 | B7: =Financial_Model!$B$3*(1+0.04)^4 -> 13157778 | C7: =Financial_Model!$B$3*(1+0.06)^4 -> 14199487 | D7: =Financial_Model!$B$3*(1+0.08)^4 -> 15301860 | E7: =Financial_Model!$B$3*(1+0.1)^4 -> 16467207 | F7: =Financial_Model!$B$3*(1+0.12)^4 -> 17697882 | G7: =Financial_Model!$B$3*(1+0.15)^4 -> 19671640 | H7: =Financial_Model!$B$3*(1+0.2)^4 -> 23322451
A8: Year 5 | B8: =Financial_Model!$B$3*(1+0.04)^5 -> 13684089 | C8: =Financial_Model!$B$3*(1+0.06)^5 -> 15051457 | D8: =Financial_Model!$B$3*(1+0.08)^5 -> 16526009 | E8: =Financial_Model!$B$3*(1+0.1)^5 -> 18113928 | F8: =Financial_Model!$B$3*(1+0.12)^5 -> 19821628 | G8: =Financial_Model!$B$3*(1+0.15)^5 -> 22622386 | H8: =Financial_Model!$B$3*(1+0.2)^5 -> 27986941
A10: SENSITIVITY: Enterprise Value (WACC vs Terminal Growth)
A11: WACC → / TGR ↓ | B11: 0.09 | C11: 0.1 | D11: 0.11 | E11: 0.12 | F11: 0.13 | G11: 0.14 | H11: 0.15
A12: 0.02 | B12: =SUM(Financial_Model!C16/(1+0.09)^1,Financial_Model!D16/(1+0.09)^2,Financial_Model!E16/(1+0.09)^3,Financial_Model!F16/(1+0.09)^4,Financial_Model!G16/(1+0.09)^5)+(Financial_Model!G16*(1+0.02)/(0.09-0.02))/(1+0.09)^5 -> 84895075 | C12: =SUM(Financial_Model!C16/(1+0.1)^1,Financial_Model!D16/(1+0.1)^2,Financial_Model!E16/(1+0.1)^3,Financial_Model!F16/(1+0.1)^4,Financial_Model!G16/(1+0.1)^5)+(Financial_Model!G16*(1+0.02)/(0.1-0.02))/(1+0.1)^5 -> 73880710 | D12: =SUM(Financial_Model!C16/(1+0.11)^1,Financial_Model!D16/(1+0.11)^2,Financial_Model!E16/(1+0.11)^3,Financial_Model!F16/(1+0.11)^4,Financial_Model!G16/(1+0.11)^5)+(Financial_Model!G16*(1+0.02)/(0.11-0.02))/(1+0.11)^5 -> 65326725 | E12: =SUM(Financial_Model!C16/(1+0.12)^1,Financial_Model!D16/(1+0.12)^2,Financial_Model!E16/(1+0.12)^3,Financial_Model!F16/(1+0.12)^4,Financial_Model!G16/(1+0.12)^5)+(Financial_Model!G16*(1+0.02)/(0.12-0.02))/(1+0.12)^5 -> 58494474 | F12: =SUM(Financial_Model!C16/(1+0.13)^1,Financial_Model!D16/(1+0.13)^2,Financial_Model!E16/(1+0.13)^3,Financial_Model!F16/(1+0.13)^4,Financial_Model!G16/(1+0.13)^5)+(Financial_Model!G16*(1+0.02)/(0.13-0.02))/(1+0.13)^5 -> 52913938 | G12: =SUM(Financial_Model!C16/(1+0.14)^1,Financial_Model!D16/(1+0.14)^2,Financial_Model!E16/(1+0.14)^3,Financial_Model!F16/(1+0.14)^4,Financial_Model!G16/(1+0.14)^5)+(Financial_Model!G16*(1+0.02)/(0.14-0.02))/(1+0.14)^5 -> 48271795 | H12: =SUM(Financial_Model!C16/(1+0.15)^1,Financial_Model!D16/(1+0.15)^2,Financial_Model!E16/(1+0.15)^3,Financial_Model!F16/(1+0.15)^4,Financial_Model!G16/(1+0.15)^5)+(Financial_Model!G16*(1+0.02)/(0.15-0.02))/(1+0.15)^5 -> 44351146
A13: 0.03 | B13: =SUM(Financial_Model!C16/(1+0.09)^1,Financial_Model!D16/(1+0.09)^2,Financial_Model!E16/(1+0.09)^3,Financial_Model!F16/(1+0.09)^4,Financial_Model!G16/(1+0.09)^5)+(Financial_Model!G16*(1+0.03)/(0.09-0.03))/(1+0.09)^5 -> 96224593 | C13: =SUM(Financial_Model!C16/(1+0.1)^1,Financial_Model!D16/(1+0.1)^2,Financial_Model!E16/(1+0.1)^3,Financial_Model!F16/(1+0.1)^4,Financial_Model!G16/(1+0.1)^5)+(Financial_Model!G16*(1+0.03)/(0.1-0.03))/(1+0.1)^5 -> 82073049 | D13: =SUM(Financial_Model!C16/(1+0.11)^1,Financial_Model!D16/(1+0.11)^2,Financial_Model!E16/(1+0.11)^3,Financial_Model!F16/(1+0.11)^4,Financial_Model!G16/(1+0.11)^5)+(Financial_Model!G16*(1+0.03)/(0.11-0.03))/(1+0.11)^5 -> 71472013 | E13: =SUM(Financial_Model!C16/(1+0.12)^1,Financial_Model!D16/(1+0.12)^2,Financial_Model!E16/(1+0.12)^3,Financial_Model!F16/(1+0.12)^4,Financial_Model!G16/(1+0.12)^5)+(Financial_Model!G16*(1+0.03)/(0.12-0.03))/(1+0.12)^5 -> 63237463 | F13: =SUM(Financial_Model!C16/(1+0.13)^1,Financial_Model!D16/(1+0.13)^2,Financial_Model!E16/(1+0.13)^3,Financial_Model!F16/(1+0.13)^4,Financial_Model!G16/(1+0.13)^5)+(Financial_Model!G16*(1+0.03)/(0.13-0.03))/(1+0.13)^5 -> 56659011 | G13: =SUM(Financial_Model!C16/(1+0.14)^1,Financial_Model!D16/(1+0.14)^2,Financial_Model!E16/(1+0.14)^3,Financial_Model!F16/(1+0.14)^4,Financial_Model!G16/(1+0.14)^5)+(Financial_Model!G16*(1+0.03)/(0.14-0.03))/(1+0.14)^5 -> 51284616 | H13: =SUM(Financial_Model!C16/(1+0.15)^1,Financial_Model!D16/(1+0.15)^2,Financial_Model!E16/(1+0.15)^3,Financial_Model!F16/(1+0.15)^4,Financial_Model!G16/(1+0.15)^5)+(Financial_Model!G16*(1+0.03)/(0.15-0.03))/(1+0.15)^5 -> 46812935
A14: 0.04 | B14: =SUM(Financial_Model!C16/(1+0.09)^1,Financial_Model!D16/(1+0.09)^2,Financial_Model!E16/(1+0.09)^3,Financial_Model!F16/(1+0.09)^4,Financial_Model!G16/(1+0.09)^5)+(Financial_Model!G16*(1+0.04)/(0.09-0.04))/(1+0.09)^5 -> 1.1208592e+08 | C14: =SUM(Financial_Model!C16/(1+0.1)^1,Financial_Model!D16/(1+0.1)^2,Financial_Model!E16/(1+0.1)^3,Financial_Model!F16/(1+0.1)^4,Financial_Model!G16/(1+0.1)^5)+(Financial_Model!G16*(1+0.04)/(0.1-0.04))/(1+0.1)^5 -> 92996168 | D14: =SUM(Financial_Model!C16/(1+0.11)^1,Financial_Model!D16/(1+0.11)^2,Financial_Model!E16/(1+0.11)^3,Financial_Model!F16/(1+0.11)^4,Financial_Model!G16/(1+0.11)^5)+(Financial_Model!G16*(1+0.04)/(0.11-0.04))/(1+0.11)^5 -> 79373099 | E14: =SUM(Financial_Model!C16/(1+0.12)^1,Financial_Model!D16/(1+0.12)^2,Financial_Model!E16/(1+0.12)^3,Financial_Model!F16/(1+0.12)^4,Financial_Model!G16/(1+0.12)^5)+(Financial_Model!G16*(1+0.04)/(0.12-0.04))/(1+0.12)^5 -> 69166199 | F14: =SUM(Financial_Model!C16/(1+0.13)^1,Financial_Model!D16/(1+0.13)^2,Financial_Model!E16/(1+0.13)^3,Financial_Model!F16/(1+0.13)^4,Financial_Model!G16/(1+0.13)^5)+(Financial_Model!G16*(1+0.04)/(0.13-0.04))/(1+0.13)^5 -> 61236322 | G14: =SUM(Financial_Model!C16/(1+0.14)^1,Financial_Model!D16/(1+0.14)^2,Financial_Model!E16/(1+0.14)^3,Financial_Model!F16/(1+0.14)^4,Financial_Model!G16/(1+0.14)^5)+(Financial_Model!G16*(1+0.04)/(0.14-0.04))/(1+0.14)^5 -> 54900001 | H14: =SUM(Financial_Model!C16/(1+0.15)^1,Financial_Model!D16/(1+0.15)^2,Financial_Model!E16/(1+0.15)^3,Financial_Model!F16/(1+0.15)^4,Financial_Model!G16/(1+0.15)^5)+(Financial_Model!G16*(1+0.04)/(0.15-0.04))/(1+0.15)^5 -> 49722321
A15: 0.05 | B15: =SUM(Financial_Model!C16/(1+0.09)^1,Financial_Model!D16/(1+0.09)^2,Financial_Model!E16/(1+0.09)^3,Financial_Model!F16/(1+0.09)^4,Financial_Model!G16/(1+0.09)^5)+(Financial_Model!G16*(1+0.05)/(0.09-0.05))/(1+0.09)^5 -> 1.358779e+08 | C15: =SUM(Financial_Model!C16/(1+0.1)^1,Financial_Model!D16/(1+0.1)^2,Financial_Model!E16/(1+0.1)^3,Financial_Model!F16/(1+0.1)^4,Financial_Model!G16/(1+0.1)^5)+(Financial_Model!G16*(1+0.05)/(0.1-0.05))/(1+0.1)^5 -> 1.0828853e+08 | D15: =SUM(Financial_Model!C16/(1+0.11)^1,Financial_Model!D16/(1+0.11)^2,Financial_Model!E16/(1+0.11)^3,Financial_Model!F16/(1+0.11)^4,Financial_Model!G16/(1+0.11)^5)+(Financial_Model!G16*(1+0.05)/(0.11-0.05))/(1+0.11)^5 -> 89907879 | E15: =SUM(Financial_Model!C16/(1+0.12)^1,Financial_Model!D16/(1+0.12)^2,Financial_Model!E16/(1+0.12)^3,Financial_Model!F16/(1+0.12)^4,Financial_Model!G16/(1+0.12)^5)+(Financial_Model!G16*(1+0.05)/(0.12-0.05))/(1+0.12)^5 -> 76788859 | F15: =SUM(Financial_Model!C16/(1+0.13)^1,Financial_Model!D16/(1+0.13)^2,Financial_Model!E16/(1+0.13)^3,Financial_Model!F16/(1+0.13)^4,Financial_Model!G16/(1+0.13)^5)+(Financial_Model!G16*(1+0.05)/(0.13-0.05))/(1+0.13)^5 -> 66957961 | G15: =SUM(Financial_Model!C16/(1+0.14)^1,Financial_Model!D16/(1+0.14)^2,Financial_Model!E16/(1+0.14)^3,Financial_Model!F16/(1+0.14)^4,Financial_Model!G16/(1+0.14)^5)+(Financial_Model!G16*(1+0.05)/(0.14-0.05))/(1+0.14)^5 -> 59318806 | H15: =SUM(Financial_Model!C16/(1+0.15)^1,Financial_Model!D16/(1+0.15)^2,Financial_Model!E16/(1+0.15)^3,Financial_Model!F16/(1+0.15)^4,Financial_Model!G16/(1+0.15)^5)+(Financial_Model!G16*(1+0.05)/(0.15-0.05))/(1+0.15)^5 -> 53213585
A16: 0.06 | B16: =SUM(Financial_Model!C16/(1+0.09)^1,Financial_Model!D16/(1+0.09)^2,Financial_Model!E16/(1+0.09)^3,Financial_Model!F16/(1+0.09)^4,Financial_Model!G16/(1+0.09)^5)+(Financial_Model!G16*(1+0.06)/(0.09-0.06))/(1+0.09)^5 -> 1.7553121e+08 | C16: =SUM(Financial_Model!C16/(1+0.1)^1,Financial_Model!D16/(1+0.1)^2,Financial_Model!E16/(1+0.1)^3,Financial_Model!F16/(1+0.1)^4,Financial_Model!G16/(1+0.1)^5)+(Financial_Model!G16*(1+0.06)/(0.1-0.06))/(1+0.1)^5 -> 1.3122708e+08 | D16: =SUM(Financial_Model!C16/(1+0.11)^1,Financial_Model!D16/(1+0.11)^2,Financial_Model!E16/(1+0.11)^3,Financial_Model!F16/(1+0.11)^4,Financial_Model!G16/(1+0.11)^5)+(Financial_Model!G16*(1+0.06)/(0.11-0.06))/(1+0.11)^5 -> 1.0465657e+08 | E16: =SUM(Financial_Model!C16/(1+0.12)^1,Financial_Model!D16/(1+0.12)^2,Financial_Model!E16/(1+0.12)^3,Financial_Model!F16/(1+0.12)^4,Financial_Model!G16/(1+0.12)^5)+(Financial_Model!G16*(1+0.06)/(0.12-0.06))/(1+0.12)^5 -> 86952407 | F16: =SUM(Financial_Model!C16/(1+0.13)^1,Financial_Model!D16/(1+0.13)^2,Financial_Model!E16/(1+0.13)^3,Financial_Model!F16/(1+0.13)^4,Financial_Model!G16/(1+0.13)^5)+(Financial_Model!G16*(1+0.06)/(0.13-0.06))/(1+0.13)^5 -> 74314353 | G16: =SUM(Financial_Model!C16/(1+0.14)^1,Financial_Model!D16/(1+0.14)^2,Financial_Model!E16/(1+0.14)^3,Financial_Model!F16/(1+0.14)^4,Financial_Model!G16/(1+0.14)^5)+(Financial_Model!G16*(1+0.06)/(0.14-0.06))/(1+0.14)^5 -> 64842311 | H16: =SUM(Financial_Model!C16/(1+0.15)^1,Financial_Model!D16/(1+0.15)^2,Financial_Model!E16/(1+0.15)^3,Financial_Model!F16/(1+0.15)^4,Financial_Model!G16/(1+0.15)^5)+(Financial_Model!G16*(1+0.06)/(0.15-0.06))/(1+0.15)^5 -> 57480685
A18: SCENARIO ANALYSIS
A19: Scenario | B19: Rev Growth | C19: Cost Inflation | D19: WACC | E19: Year 5 Revenue ($) | F19: Year 5 Profit ($) | G19: EV ($)
A20: Upside | B20: 0.15 | C20: 0.04 | D20: 0.1 | E20: =Financial_Model!$B$3*(1+B20)^5 -> 22622386 | F20: =E20*(1-C20)*5*0.3 -> 32576236 | G20: =IFERROR(F20*(1+Assumptions!$B$9)/(D20-Assumptions!$B$9),0) -> -32576415
A21: Base Case | B21: 0.08 | C21: 0.06 | D21: 0.12 | E21: =Financial_Model!$B$3*(1+B21)^5 -> 16526009 | F21: =E21*(1-C21)*5*0.3 -> 23301672 | G21: =IFERROR(F21*(1+Assumptions!$B$9)/(D21-Assumptions!$B$9),0) -> -23301803
A22: Downside | B22: 0.04 | C22: 0.09 | D22: 0.14 | E22: =Financial_Model!$B$3*(1+B22)^5 -> 13684089 | F22: =E22*(1-C22)*5*0.3 -> 18678782 | G22: =IFERROR(F22*(1+Assumptions!$B$9)/(D22-Assumptions!$B$9),0) -> -18678888
A23: Stress | B23: 0 | C23: 0.12 | D23: 0.16 | E23: =Financial_Model!$B$3*(1+B23)^5 -> 11247324 | F23: =E23*(1-C23)*5*0.3 -> 14846468 | G23: =IFERROR(F23*(1+Assumptions!$B$9)/(D23-Assumptions!$B$9),0) -> -14846554

Sheet Dashboard
A1: 🏠 EXECUTIVE DASHBOARD | Financial Model Summary
A3: Total Revenue | C3: Total Profit | E3: Avg Margin | G3: Enterprise Value (DCF) | I3: EV / EBITDA
A4: =Calculations!B3 -> 11247324 | C4: =Calculations!B4 -> 5657718.6 | E4: =Calculations!B6 -> 0.46284394 | G4: =Valuation_DCF!B16 -> 69166199 | I4: =Valuation_DCF!B17 -> 12.374076
A6: REGIONAL PERFORMANCE
A7: Region | B7: Revenue ($) | C7: Profit ($) | D7: Margin (%) | E7: vs. Average
A8: Dhaka | B8: =Calculations!B12 -> Revenue ($) | C8: =Calculations!D12 -> Profit ($) | D8: =Calculations!E12 -> Margin (%) | E8: =IFERROR(D8-AVERAGE(Calculations!E13:E17),0) -> 0
A9: Chittagong | B9: =Calculations!B13 -> 1744945.5 | C9: =Calculations!D13 -> 766192.98 | D9: =Calculations!E13 -> 0.43909279 | E9: =IFERROR(D9-AVERAGE(Calculations!E13:E17),0) -> -0.05628042
A10: Sylhet | B10: =Calculations!B14 -> 2422198.9 | C10: =Calculations!D14 -> 1234702.8 | D10: =Calculations!E14 -> 0.5097446 | E10: =IFERROR(D10-AVERAGE(Calculations!E13:E17),0) -> 0.014371392
A11: Khulna | B11: =Calculations!B15 -> 2188732.1 | C11: =Calculations!D15 -> 1125451.9 | D11: =Calculations!E15 -> 0.51420267 | E11: =IFERROR(D11-AVERAGE(Calculations!E13:E17),0) -> 0.018829458
A12: Rajshahi | B12: =Calculations!B16 -> 2796225.5 | C12: =Calculations!D16 -> 1352501.4 | D12: =Calculations!E16 -> 0.48368822 | E12: =IFERROR(D12-AVERAGE(Calculations!E13:E17),0) -> -0.011684986
A15: 5-YEAR FORECAST SNAPSHOT
A16: Metric | B16: Base | C16: Yr 1 | D16: Yr 2 | E16: Yr 3 | F16: Yr 4 | G16: Yr 5 | H16: CAGR
A17: Revenue ($) | B17: =Financial_Model!B3 -> 11247324 | C17: =Financial_Model!C3 -> 12147110 | D17: =Financial_Model!D3 -> 13118879 | E17: =Financial_Model!E3 -> 14168389 | F17: =Financial_Model!F3 -> 15301860 | G17: =Financial_Model!G3 -> 16526009 | H17: =Financial_Model!H3 -> 0.08
A18: Net Income ($) | B18: =Financial_Model!B10 -> 4471684.2 | C18: =Financial_Model!C10 -> 4919942.5 | D18: =Financial_Model!D10 -> 5409492.8 | E18: =Financial_Model!E10 -> 5943964.4 | F18: =Financial_Model!F10 -> 6527296.5 | G18: =Financial_Model!G10 -> 7163764 | H18: =Financial_Model!H10 -> 0.098838908
A19: FCF ($) | B19: =Financial_Model!B16 -> 4171684.2 | C19: =Financial_Model!C16 -> 4511968.2 | D19: =Financial_Model!D16 -> 4992880.5 | E19: =Financial_Model!E16 -> 5518023.2 | F19: =Financial_Model!F16 -> 6091279.9 | G19: =Financial_Model!G16 -> 6716866.2 | H19: =Financial_Model!H16 -> 0.099945212
